collection_utils/__init__.py
collection_utils/utils.py
bear_collection_utils-0.1.0.dist-info/METADATA
bear_collection_utils-0.1.0.dist-info/WHEEL
bear_collection_utils-0.1.0.dist-info/top_level.txt
bear_collection_utils-0.1.0.dist-info/RECORD
